GenIText/PA_track.py
GenIText/__init__.py
GenIText/cli.py
GenIText/config_editor.py
GenIText/utils.py
GenIText/configs/blipv2_config.yaml
GenIText/configs/llava_config.yaml
GenIText/configs/vit_gpt2_config.yaml
GenIText/models/BLIPv2.py
GenIText/models/__init__.py
GenIText/models/base.py
GenIText/models/clip_reranking.py
GenIText/models/llava.py
GenIText/models/vit_gpt2.py
GenIText/pipelines/__init__.py
GenIText/pipelines/caption.py
GenIText/prompt_refiner/GA_LLM_Judge.py
GenIText/prompt_refiner/GA_refiner.py
GenIText/prompt_refiner/GA_utils.py
GenIText/prompt_refiner/__init__.py
GenIText/prompt_refiner/prompts.py
genitext-0.4.2.dist-info/licenses/LICENSE
genitext-0.4.2.dist-info/METADATA
genitext-0.4.2.dist-info/WHEEL
genitext-0.4.2.dist-info/entry_points.txt
genitext-0.4.2.dist-info/top_level.txt
genitext-0.4.2.dist-info/RECORD
