Metadata-Version: 2.4
Name: genitext
Version: 0.4.2
Summary: A CLI tool for generating high-quality image-text pairs for AI training
Home-page: https://github.com/CodeKnight314/GenIText
Author: Richard Tang
Author-email: Richard Tang <richardgtang@gmail.com>
License: MIT License
Project-URL: Homepage, https://github.com/CodeKnight314/GenIText
Project-URL: Repository, https://github.com/CodeKnight314/GenIText
Project-URL: Issues, https://github.com/CodeKnight314/GenIText/issues
Classifier: Programming Language :: Python :: 3
Classifier: License :: OSI Approved :: MIT License
Classifier: Operating System :: OS Independent
Classifier: Development Status :: 4 - Beta
Classifier: Intended Audience :: Developers
Classifier: Topic :: Scientific/Engineering :: Artificial Intelligence
Requires-Python: >=3.8
License-File: LICENSE
Requires-Dist: torch>=2.0.0
Requires-Dist: torchvision>=0.15.0
Requires-Dist: Pillow>=9.0.0
Requires-Dist: tqdm>=4.64.0
Requires-Dist: matplotlib>=3.6.0
Requires-Dist: kagglehub>=0.1.0
Requires-Dist: pyyaml>=6.0
Requires-Dist: bitsandbytes>=0.41.0
Requires-Dist: accelerate>=0.26.0
Requires-Dist: numpy>=1.21.0
Requires-Dist: transformers>=4.21.0
Requires-Dist: typing-extensions>=4.5.0
Requires-Dist: ollama>=0.1.7
Requires-Dist: prompt-toolkit>=3.0.0
Requires-Dist: click>=8.0.0
Dynamic: author
Dynamic: home-page
Dynamic: license-file
Dynamic: requires-python
